pandas_fast_nested_looper/__init__.py
pandas_fast_nested_looper/pandas_fast_nested_looper.py
pandas_fast_nested_looper-0.0.9.dist-info/LICENSE
pandas_fast_nested_looper-0.0.9.dist-info/METADATA
pandas_fast_nested_looper-0.0.9.dist-info/WHEEL
pandas_fast_nested_looper-0.0.9.dist-info/top_level.txt
pandas_fast_nested_looper-0.0.9.dist-info/RECORD
