Metadata-Version: 2.1
Name: pandas-fast-nested-looper
Version: 0.0.9
Summary: pandas-fast-nested-looper
Home-page: https://github.com/ganbaaelmer/pandas-fast-nested-looper.git
Author: Ganbaatar Bold
Author-email: elmerganbaa <elmerganbaa@gmail.com>
Project-URL: Homepage, https://github.com/ganbaaelmer/pandas-fast-nested-looper.git
Project-URL: Issues, https://github.com/ganbaaelmer/pandas-fast-nested-looper.git
Classifier: Programming Language :: Python :: 3
Classifier: License :: OSI Approved :: MIT License
Classifier: Operating System :: OS Independent
Requires-Python: >=3.6
License-File: LICENSE
